LICENSE
MANIFEST.in
README.rst
setup.py
coa_django_countable_field.egg-info/PKG-INFO
coa_django_countable_field.egg-info/SOURCES.txt
coa_django_countable_field.egg-info/dependency_links.txt
coa_django_countable_field.egg-info/top_level.txt
countable_field/__init__.py
countable_field/widgets.py
countable_field/static/countable_field/css/styles.css
countable_field/static/countable_field/js/scripts.js
example_project/__init__.py
example_project/forms.py
example_project/settings.py
example_project/urls.py
example_project/views.py
example_project/wsgi.py
tests/__init__.py
tests/test_settings.py
tests/tests.py